CIM14/CombinedVersion.py
CIM14/Element.py
CIM14/__init__.py
CIM14/CDPSM/__init__.py
CIM14/CDPSM/Balanced/Element.py
CIM14/CDPSM/Balanced/__init__.py
CIM14/CDPSM/Balanced/IEC61968/__init__.py
CIM14/CDPSM/Balanced/IEC61968/AssetModels/CableInfo.py
CIM14/CDPSM/Balanced/IEC61968/AssetModels/ConcentricNeutralCableInfo.py
CIM14/CDPSM/Balanced/IEC61968/AssetModels/ConductorInfo.py
CIM14/CDPSM/Balanced/IEC61968/AssetModels/DistributionWindingTest.py
CIM14/CDPSM/Balanced/IEC61968/AssetModels/OpenCircuitTest.py
CIM14/CDPSM/Balanced/IEC61968/AssetModels/OverheadConductorInfo.py
CIM14/CDPSM/Balanced/IEC61968/AssetModels/ShortCircuitTest.py
CIM14/CDPSM/Balanced/IEC61968/AssetModels/TapeShieldCableInfo.py
CIM14/CDPSM/Balanced/IEC61968/AssetModels/ToWindingSpec.py
CIM14/CDPSM/Balanced/IEC61968/AssetModels/TransformerInfo.py
CIM14/CDPSM/Balanced/IEC61968/AssetModels/WindingInfo.py
CIM14/CDPSM/Balanced/IEC61968/AssetModels/WireArrangement.py
CIM14/CDPSM/Balanced/IEC61968/AssetModels/WireType.py
CIM14/CDPSM/Balanced/IEC61968/AssetModels/__init__.py
CIM14/CDPSM/Balanced/IEC61968/Common/GeoLocation.py
CIM14/CDPSM/Balanced/IEC61968/Common/Location.py
CIM14/CDPSM/Balanced/IEC61968/Common/PositionPoint.py
CIM14/CDPSM/Balanced/IEC61968/Common/__init__.py
CIM14/CDPSM/Balanced/IEC61968/WiresExt/DistributionLineSegment.py
CIM14/CDPSM/Balanced/IEC61968/WiresExt/DistributionTapChanger.py
CIM14/CDPSM/Balanced/IEC61968/WiresExt/DistributionTransformer.py
CIM14/CDPSM/Balanced/IEC61968/WiresExt/DistributionTransformerWinding.py
CIM14/CDPSM/Balanced/IEC61968/WiresExt/PerLengthPhaseImpedance.py
CIM14/CDPSM/Balanced/IEC61968/WiresExt/PerLengthSequenceImpedance.py
CIM14/CDPSM/Balanced/IEC61968/WiresExt/PhaseImpedanceData.py
CIM14/CDPSM/Balanced/IEC61968/WiresExt/TransformerBank.py
CIM14/CDPSM/Balanced/IEC61968/WiresExt/WindingPiImpedance.py
CIM14/CDPSM/Balanced/IEC61968/WiresExt/__init__.py
CIM14/CDPSM/Balanced/IEC61970/IEC61970CIMVersion.py
PyCIM-15.15.0.dist-info/DESCRIPTION.rst
PyCIM-15.15.0.dist-info/METADATA
PyCIM-15.15.0.dist-info/RECORD
PyCIM-15.15.0.dist-info/WHEEL
PyCIM-15.15.0.dist-info/metadata.json
PyCIM-15.15.0.dist-info/top_level.txt
PyCIM-15.15.0.dist-info/zip-safe
