Metadata-Version: 2.0
Name: PyCIM
Version: 15.15.0
Summary: Python implementation of the Common Information Model.
Home-page: https://github.com/rwl/PyCIM
Author: Richard Lincoln
Author-email: r.w.lincoln@gmail.com
License: MIT
Platform: UNKNOWN
Classifier: Development Status :: 5 - Production/Stable
Classifier: Intended Audience :: Developers
Classifier: Intended Audience :: Science/Research
Classifier: Topic :: Scientific/Engineering
Classifier: Topic :: Scientific/Engineering :: Interface Engine/Protocol Translator
Classifier: License :: OSI Approved :: MIT License
Classifier: Programming Language :: Python :: 2
Classifier: Programming Language :: Python :: 2.6
Classifier: Programming Language :: Python :: 2.7
Classifier: Programming Language :: Python :: 3
Classifier: Programming Language :: Python :: 3.4
Classifier: Programming Language :: Python :: 3.5
Classifier: Programming Language :: Python :: 3.6
Provides-Extra: build
Requires-Dist: twine; extra == 'build'
Provides-Extra: test
Requires-Dist: pytest; extra == 'test'
